{
  "collectionName": "components_sections_serialization_list_sections",
  "info": {
    "displayName": "Serialization section",
    "icon": "table",
    "description": ""
  },
  "options": {},
  "attributes": {
    "title": {
      "type": "string"
    },
    "text_content": {
      "type": "richtext"
    },
    "serialization": {
      "type": "json"
    },
    "background": {
      "type": "enumeration",
      "enum": [
        "normal",
        "blank"
      ],
      "default": "normal"
    }
  }
}
